clr_utils/__init__.py
spatialcl/__init__.py
spatialcl/clearn.py
spatialcl/uncertainty.py
spatialcl/uwcl.py
spatialcl/_config/__init__.py
spatialcl/_config/config.py
spatialcl/_config/parameter.yaml
spatialcl/_dto/__init__.py
spatialcl/_dto/cldto.py
spatialcl/_dto/config.py
spatialcl/_dto/image_label_dto.py
spatialcl/_dto/mask.py
spatialcl-0.1.2.2.dist-info/licenses/LICENSE
thermal/__init__.py
thermal/augmentor.py
spatialcl-0.1.2.2.dist-info/METADATA
spatialcl-0.1.2.2.dist-info/WHEEL
spatialcl-0.1.2.2.dist-info/top_level.txt
spatialcl-0.1.2.2.dist-info/RECORD
