Metadata-Version: 2.4
Name: spatialcl
Version: 0.1.2.2
Summary: Plug-and-play contrastive learning framework designed for spatially structured modalities.
Author-email: Félix Olémou <olemoufelix1@gmail.com>, Éric Hervet <eric.hervet@umoncton.ca>, Ghazal Rouhafzay <ghazal.rouhafzay@umoncton.ca>
License: MIT
Project-URL: Homepage, https://github.com/Olemou/SpatialCL
Project-URL: Documentation, https://github.com/Olemou/SpatialCL/blob/master/README.md
Project-URL: Repository, https://github.com/Olemou/SpatialCL
Project-URL: Bug Tracker, https://github.com/Olemou/SpatialCL/issues
Keywords: computer-vision,contrastive-learning,uncertainty-estimation
Classifier: Intended Audience :: Science/Research
Classifier: License :: OSI Approved :: MIT License
Classifier: Programming Language :: Python :: 3
Classifier: Programming Language :: Python :: 3.12
Classifier: Topic :: Scientific/Engineering :: Artificial Intelligence
Requires-Python: >=3.12
License-File: LICENSE
Requires-Dist: torch>=1.9.0
Requires-Dist: torchvision>=0.10.0
Requires-Dist: numpy>=1.21.0
Requires-Dist: scipy>=1.7.0
Requires-Dist: tqdm>=4.60.0
Requires-Dist: opencv-python>=4.5.0
Requires-Dist: Pillow>=9.0.0
Requires-Dist: pyyaml>=6.0.3
Dynamic: license-file
